django_emailmeld-0.0.6.dist-info/DESCRIPTION.rst
django_emailmeld-0.0.6.dist-info/METADATA
django_emailmeld-0.0.6.dist-info/RECORD
django_emailmeld-0.0.6.dist-info/WHEEL
django_emailmeld-0.0.6.dist-info/metadata.json
django_emailmeld-0.0.6.dist-info/top_level.txt
emailmeld/__init__.py
emailmeld/admin.py
emailmeld/models.py
emailmeld/sender.py
emailmeld/tasks.py
emailmeld/views.py
emailmeld/migrations/0001_initial.py
emailmeld/migrations/0002_auto_20151021_0334.py
emailmeld/migrations/__init__.py
emailmeld/south_migrations/0001_initial.py
emailmeld/south_migrations/__init__.py
emailmeld/templates/emailmeld.html
emailmeld/templates/emailmeld.md
emailmeld/templates/emailmeld.txt
